sensei/__init__.py
sensei/cli.py
sensei/db.py
sensei/init.py
sensei/mcp.py
sensei/models.py
sensei/srs.py
sensei/migrations/001_initial.sql
sensei/migrations/002_references.sql
sensei/migrations/__init__.py
sensei/templates/CLAUDE.md
sensei/templates/SKILL.md
sensei/templates/mcp.json
notice_me_sensei-0.2.0.dist-info/METADATA
notice_me_sensei-0.2.0.dist-info/WHEEL
notice_me_sensei-0.2.0.dist-info/entry_points.txt
notice_me_sensei-0.2.0.dist-info/licenses/LICENSE
notice_me_sensei-0.2.0.dist-info/RECORD
