Metadata-Version: 2.4
Name: notice-me-sensei
Version: 0.2.0
Summary: AI-powered personal learning coach with spaced repetition
Project-URL: Homepage, https://github.com/tdfirth/sensei
Project-URL: Repository, https://github.com/tdfirth/sensei
Project-URL: Issues, https://github.com/tdfirth/sensei/issues
Author: Tom Firth
License-Expression: MIT
License-File: LICENSE
Keywords: ai,claude,learning,mcp,spaced-repetition,srs,study
Classifier: Development Status :: 4 - Beta
Classifier: Environment :: Console
Classifier: Intended Audience :: Developers
Classifier: Intended Audience :: Education
Classifier: License :: OSI Approved :: MIT License
Classifier: Operating System :: OS Independent
Classifier: Programming Language :: Python :: 3
Classifier: Programming Language :: Python :: 3.11
Classifier: Programming Language :: Python :: 3.12
Classifier: Programming Language :: Python :: 3.13
Classifier: Topic :: Education
Classifier: Typing :: Typed
Requires-Python: >=3.11
Requires-Dist: fastmcp>=2.0
Requires-Dist: pydantic>=2.0
Requires-Dist: typer>=0.21
